odoo8_addon_web_form_sticky_header-8.0.1.0.0-py2.7-nspkg.pth
odoo8_addon_web_form_sticky_header-8.0.1.0.0.dist-info/DESCRIPTION.rst
odoo8_addon_web_form_sticky_header-8.0.1.0.0.dist-info/METADATA
odoo8_addon_web_form_sticky_header-8.0.1.0.0.dist-info/RECORD
odoo8_addon_web_form_sticky_header-8.0.1.0.0.dist-info/WHEEL
odoo8_addon_web_form_sticky_header-8.0.1.0.0.dist-info/metadata.json
odoo8_addon_web_form_sticky_header-8.0.1.0.0.dist-info/namespace_packages.txt
odoo8_addon_web_form_sticky_header-8.0.1.0.0.dist-info/top_level.txt
odoo_addons/web_form_sticky_header/README.rst
odoo_addons/web_form_sticky_header/__init__.py
odoo_addons/web_form_sticky_header/__openerp__.py
odoo_addons/web_form_sticky_header/images/fixed_header.png
odoo_addons/web_form_sticky_header/static/description/icon.png
odoo_addons/web_form_sticky_header/static/src/css/sticky_header.css
odoo_addons/web_form_sticky_header/views/templates.xml
